about/__about__.py
about/__init__.py
commands/__init__.py
commands/file_arranger.py
commands/file_extractor.py
commands/file_organizer.py
commands/removing_emptyfolder.py
run/__init__.py
run/run.py
file_manager-0.0.1.dist-info/METADATA
file_manager-0.0.1.dist-info/WHEEL
file_manager-0.0.1.dist-info/entry_points.txt
file_manager-0.0.1.dist-info/top_level.txt
file_manager-0.0.1.dist-info/RECORD
