Metadata-Version: 2.1
Name: file-manager
Version: 0.0.1
Summary: CLI for organizing files
Home-page: https://github.com/Saurav-Paul/File-Manager-python-module
Author: Saurav Paul
Author-email: sauravpaul.sunny@gmail.com
License: MIT License
Keywords: file manager
Platform: UNKNOWN
Classifier: Development Status :: 4 - Beta
Classifier: Environment :: Console
Classifier: Intended Audience :: End Users/Desktop
Classifier: Operating System :: POSIX :: Linux
Classifier: Operating System :: MacOS :: MacOS X
Classifier: License :: OSI Approved :: MIT License
Requires-Python: >=3.5
